<?xml version="1.0" encoding="UTF-8"?>
<metadata xml:lang="es"><Esri><CreaDate>20230702</CreaDate><CreaTime>11430100</CreaTime><ArcGISFormat>1.0</ArcGISFormat><SyncOnce>TRUE</SyncOnce><DataProperties><lineage><Process ToolSource="c:\program files\arcgis\pro\Resources\ArcToolbox\toolboxes\Conversion Tools.tbx\RasterToPolygon" Date="20230702" Time="114301">RasterToPolygon C:\Workspace\LagoValencia\LagoValencia.gdb\MNDWI_2000_classified C:\Workspace\LagoValencia\MNDWI_2000_classified.shp NO_SIMPLIFY Value SINGLE_OUTER_PART #</Process></lineage></DataProperties></Esri></metadata>
